aiar/__init__.py
aiar/aiar_base.py
aiar-0.1.9.dist-info/METADATA
aiar-0.1.9.dist-info/WHEEL
aiar-0.1.9.dist-info/entry_points.txt
aiar-0.1.9.dist-info/licenses/LICENSE
aiar-0.1.9.dist-info/RECORD
