Metadata-Version: 2.4
Name: aiar
Version: 0.1.9
Summary: AI Archive is a format and a tool for bundling a directory structure and its files into a single, executable bash/zsh script. It's designed to make sending and receiving file collections in a chat-based or text-only environment—like interacting with an LLM—as simple as copying and pasting a single block of text.
Project-URL: Homepage, https://github.com/owebeeone/aiar
Project-URL: Issues, https://github.com/owebeeone/aiar/issues
Author-email: Gianni Mariani <gianni@mariani.ws>
License: MIT
License-File: LICENSE
Classifier: Intended Audience :: Developers
Classifier: License :: OSI Approved :: MIT License
Classifier: Operating System :: OS Independent
Classifier: Programming Language :: Python :: 3
Classifier: Programming Language :: Python :: 3.9
Classifier: Programming Language :: Python :: 3.10
Classifier: Programming Language :: Python :: 3.11
Classifier: Programming Language :: Python :: 3.12
Classifier: Topic :: Software Development :: Libraries :: Python Modules
Classifier: Topic :: System :: Archiving
Requires-Python: >=3.9
Requires-Dist: pathspec>=0.12.1
Provides-Extra: dev
Requires-Dist: mypy; extra == 'dev'
Requires-Dist: ruff; extra == 'dev'
